cnds.cpython-313-darwin.so
pynds/config.py
pynds/window.py
pynds/memory.py
pynds/pynds.py
pynds/__init__.py
pynds/button.py
pynds-0.0.3.dist-info/RECORD
pynds-0.0.3.dist-info/WHEEL
pynds-0.0.3.dist-info/top_level.txt
pynds-0.0.3.dist-info/METADATA
pynds-0.0.3.dist-info/licenses/LICENSE
