Metadata-Version: 2.4
Name: pynds
Version: 0.0.3
Summary: Python interface for emulated Nintendo DS
Home-page: https://github.com/unexploredtest/PyNDS
Author: unexploredtest
Author-email: unexploredtest <unexploredtest@tutanota.com>
License:                     GNU GENERAL PUBLIC LICENSE
Project-URL: Homepage, https://github.com/unexploredtest/PyNDS
Classifier: Programming Language :: Python :: 3.9
Classifier: Programming Language :: Python :: 3.10
Classifier: Programming Language :: Python :: 3.11
Classifier: Programming Language :: Python :: 3.12
Classifier: Programming Language :: Python :: 3.13
Classifier: Programming Language :: Python :: 3.14
Requires-Python: >=3.9
License-File: LICENSE
Requires-Dist: numpy
Requires-Dist: pygame
Dynamic: author
Dynamic: description
Dynamic: description-content-type
Dynamic: home-page
Dynamic: license-file
